{"last_link_id":182,"nodes":[{"mode":0,"outputs":[{"name":"LATENT","links":[149],"label":"LATENT","type":"LATENT","localized_name":"LATENT"}],"size":[270,262],"pos":[1601.7471923828125,985.068603515625],"widgets_values":[7567358653673,"fixed",4,1,"ipndm","sgm_uniform",1],"inputs":[{"name":"model","link":123,"label":"model","type":"MODEL","localized_name":"model"},{"name":"positive","link":144,"label":"positive","type":"CONDITIONING","localized_name":"positive"},{"name":"negative","link":145,"label":"negative","type":"CONDITIONING","localized_name":"negative"},{"name":"latent_image","link":143,"label":"latent_image","type":"LATENT","localized_name":"latent_image"},{"widget":{"name":"seed"},"name":"seed","label":"seed","type":"INT","localized_name":"seed"},{"widget":{"name":"steps"},"name":"steps","label":"steps","type":"INT","localized_name":"steps"},{"widget":{"name":"cfg"},"name":"cfg","label":"cfg","type":"FLOAT","localized_name":"cfg"},{"widget":{"name":"sampler_name"},"name":"sampler_name","label":"sampler_name","type":"COMBO","localized_name":"sampler_name"},{"widget":{"name":"scheduler"},"name":"scheduler","label":"scheduler","type":"COMBO","localized_name":"scheduler"},{"widget":{"name":"denoise"},"name":"denoise","label":"denoise","type":"FLOAT","localized_name":"denoise"}],"flags":{},"id":8,"type":"KSampler","properties":{"widget_ue_connectable":{},"Node name for S&R":"KSampler"},"order":17},{"mode":0,"outputs":[{"name":"MODEL","links":[123],"label":"MODEL","type":"MODEL","localized_name":"MODEL"}],"size":[270,58],"pos":[1258.5234375,864.0829467773438],"widgets_values":[8],"inputs":[{"name":"model","link":174,"label":"model","type":"MODEL","localized_name":"model"},{"widget":{"name":"shift"},"name":"shift","label":"shift","type":"FLOAT","localized_name":"shift"}],"flags":{},"id":32,"type":"ModelSamplingSD3","properties":{"widget_ue_connectable":{},"Node name for S&R":"ModelSamplingSD3"},"order":13},{"mode":0,"outputs":[{"name":"CONDITIONING","links":[137],"label":"CONDITIONING","type":"CONDITIONING","localized_name":"CONDITIONING"}],"size":[391.07098388671875,88],"pos":[742.6182250976562,1414.9295654296875],"widgets_values":[""],"inputs":[{"name":"clip","link":153,"label":"clip","type":"CLIP","localized_name":"clip"},{"widget":{"name":"text"},"name":"text","label":"text","type":"STRING","localized_name":"text"}],"flags":{},"id":10,"type":"CLIPTextEncode","title":"Negative Prompt (leave blank cuz 1 CFG)","properties":{"widget_ue_connectable":{},"Node name for S&R":"CLIPTextEncode"},"order":10},{"mode":0,"outputs":[{"name":"positive","links":[144],"label":"positive","type":"CONDITIONING","localized_name":"positive"},{"name":"negative","links":[145],"label":"negative","type":"CONDITIONING","localized_name":"negative"},{"name":"latent","links":[143],"label":"latent","type":"LATENT","localized_name":"latent"},{"name":"trim_latent","links":[],"label":"trim_latent","type":"INT","localized_name":"trim_latent"}],"size":[270,254],"pos":[1265.000244140625,992.2266845703125],"widgets_values":[512,512,65,1,1],"inputs":[{"name":"positive","link":136,"label":"positive","type":"CONDITIONING","localized_name":"positive"},{"name":"negative","link":137,"label":"negative","type":"CONDITIONING","localized_name":"negative"},{"name":"vae","link":154,"label":"vae","type":"VAE","localized_name":"vae"},{"shape":7,"name":"control_video","link":141,"label":"control_video","type":"IMAGE","localized_name":"control_video"},{"shape":7,"name":"control_masks","link":148,"label":"control_masks","type":"MASK","localized_name":"control_masks"},{"shape":7,"name":"reference_image","label":"reference_image","type":"IMAGE","localized_name":"reference_image"},{"widget":{"name":"width"},"name":"width","label":"width","type":"INT","localized_name":"width"},{"widget":{"name":"height"},"name":"height","label":"height","type":"INT","localized_name":"height"},{"widget":{"name":"length"},"name":"length","link":181,"label":"length","type":"INT","localized_name":"length"},{"widget":{"name":"batch_size"},"name":"batch_size","label":"batch_size","type":"INT","localized_name":"batch_size"},{"widget":{"name":"strength"},"name":"strength","label":"strength","type":"FLOAT","localized_name":"strength"}],"flags":{},"id":28,"type":"WanVaceToVideo","properties":{"widget_ue_connectable":{"length":true},"Node name for S&R":"WanVaceToVideo"},"order":16},{"outputs":[],"color":"#432","widgets_values":["T2V? WanVaceToVideo strength = 0.0\nI2V? WanVaceToVideo strength = 1.0\n(Can experiment with values 0-1)\n\n\n\n"],"inputs":[],"flags":{},"type":"Note","mode":0,"bgcolor":"#653","size":[261.9561462402344,140.74337768554688],"pos":[1602.0777587890625,788.3606567382812],"id":36,"properties":{"widget_ue_connectable":{}},"order":0},{"mode":0,"outputs":[{"name":"images","links":[141],"label":"images","type":"IMAGE","localized_name":"images"},{"name":"masks","links":[148],"label":"masks","type":"MASK","localized_name":"masks"}],"size":[329.9634704589844,190],"pos":[748.0418090820312,728.7391967773438],"widgets_values":[65,0.5,0,-1],"inputs":[{"shape":7,"name":"start_image","link":175,"label":"start_image","type":"IMAGE","localized_name":"start_image"},{"shape":7,"name":"end_image","link":163,"label":"end_image","type":"IMAGE","localized_name":"end_image"},{"shape":7,"name":"control_images","label":"control_images","type":"IMAGE","localized_name":"control_images"},{"shape":7,"name":"inpaint_mask","label":"inpaint_mask","type":"MASK","localized_name":"inpaint_mask"},{"widget":{"name":"num_frames"},"name":"num_frames","link":180,"label":"num_frames","type":"INT","localized_name":"num_frames"},{"widget":{"name":"empty_frame_level"},"name":"empty_frame_level","label":"empty_frame_level","type":"FLOAT","localized_name":"empty_frame_level"},{"widget":{"name":"start_index"},"shape":7,"name":"start_index","label":"start_index","type":"INT","localized_name":"start_index"},{"widget":{"name":"end_index"},"shape":7,"name":"end_index","label":"end_index","type":"INT","localized_name":"end_index"}],"flags":{},"id":34,"type":"WanVideoVACEStartToEndFrame","properties":{"widget_ue_connectable":{"num_frames":true},"Node name for S&R":"WanVideoVACEStartToEndFrame"},"order":15},{"mode":0,"outputs":[{"name":"image","label":"image","type":"IMAGE","localized_name":"image"},{"name":"mask","label":"mask","type":"MASK","localized_name":"mask"},{"name":"original_size","label":"original_size","type":"BOX","localized_name":"original_size"},{"name":"width","links":[164],"label":"width","type":"INT","localized_name":"width"},{"name":"height","links":[165],"label":"height","type":"INT","localized_name":"height"}],"size":[363.6851501464844,330],"color":"rgba(38, 73, 116, 0.7)","pos":[246.7986297607422,570.651611328125],"widgets_values":["original",1,1,"crop","lanczos","16","longest",1024,"#000000"],"inputs":[{"shape":7,"name":"image","link":176,"label":"image","type":"IMAGE","localized_name":"image"},{"shape":7,"name":"mask","label":"mask","type":"MASK","localized_name":"mask"},{"widget":{"name":"aspect_ratio"},"name":"aspect_ratio","label":"aspect_ratio","type":"COMBO","localized_name":"aspect_ratio"},{"widget":{"name":"proportional_width"},"name":"proportional_width","label":"proportional_width","type":"INT","localized_name":"proportional_width"},{"widget":{"name":"proportional_height"},"name":"proportional_height","label":"proportional_height","type":"INT","localized_name":"proportional_height"},{"widget":{"name":"fit"},"name":"fit","label":"fit","type":"COMBO","localized_name":"fit"},{"widget":{"name":"method"},"name":"method","label":"method","type":"COMBO","localized_name":"method"},{"widget":{"name":"round_to_multiple"},"name":"round_to_multiple","label":"round_to_multiple","type":"COMBO","localized_name":"round_to_multiple"},{"widget":{"name":"scale_to_side"},"name":"scale_to_side","label":"scale_to_side","type":"COMBO","localized_name":"scale_to_side"},{"widget":{"name":"scale_to_length"},"name":"scale_to_length","link":182,"label":"scale_to_length","type":"INT","localized_name":"scale_to_length"},{"widget":{"name":"background_color"},"name":"background_color","label":"background_color","type":"STRING","localized_name":"background_color"}],"flags":{},"id":41,"type":"LayerUtility: ImageScaleByAspectRatio V2","properties":{"widget_ue_connectable":{},"Node name for S&R":"LayerUtility: ImageScaleByAspectRatio V2"},"order":12},{"mode":0,"outputs":[{"name":"IMAGE","links":[168],"label":"IMAGE","type":"IMAGE","localized_name":"IMAGE"}],"size":[270,102],"pos":[1841.04638671875,1483.72900390625],"widgets_values":["down",true],"inputs":[{"name":"image1","link":177,"label":"image1","type":"IMAGE","localized_name":"image1"},{"name":"image2","link":179,"label":"image2","type":"IMAGE","localized_name":"image2"},{"widget":{"name":"direction"},"name":"direction","label":"direction","type":"COMBO","localized_name":"direction"},{"widget":{"name":"match_image_size"},"name":"match_image_size","label":"match_image_size","type":"BOOLEAN","localized_name":"match_image_size"}],"flags":{},"id":43,"type":"ImageConcanate","properties":{"widget_ue_connectable":{},"Node name for S&R":"ImageConcanate"},"order":11},{"mode":0,"outputs":[{"name":"IMAGE","links":[170],"label":"IMAGE","type":"IMAGE","localized_name":"IMAGE"}],"size":[270,102],"pos":[2251.30126953125,1472.032958984375],"widgets_values":["right",true],"inputs":[{"name":"image1","link":168,"label":"image1","type":"IMAGE","localized_name":"image1"},{"name":"image2","link":169,"label":"image2","type":"IMAGE","localized_name":"image2"},{"widget":{"name":"direction"},"name":"direction","label":"direction","type":"COMBO","localized_name":"direction"},{"widget":{"name":"match_image_size"},"name":"match_image_size","label":"match_image_size","type":"BOOLEAN","localized_name":"match_image_size"}],"flags":{},"id":44,"type":"ImageConcanate","properties":{"widget_ue_connectable":{},"Node name for S&R":"ImageConcanate"},"order":19},{"mode":0,"outputs":[{"name":"IMAGE","links":[169,171],"label":"IMAGE","type":"IMAGE","localized_name":"IMAGE"}],"size":[140,46],"pos":[1992.03662109375,1078.155029296875],"widgets_values":[],"inputs":[{"name":"samples","link":149,"label":"samples","type":"LATENT","localized_name":"samples"},{"name":"vae","link":155,"label":"vae","type":"VAE","localized_name":"vae"}],"flags":{},"id":11,"type":"VAEDecode","properties":{"widget_ue_connectable":{},"Node name for S&R":"VAEDecode"},"order":18},{"mode":0,"outputs":[{"name":"Filenames","label":"Filenames","type":"VHS_FILENAMES","localized_name":"Filenames"}],"size":[214.7587890625,477.4943542480469],"pos":[3208.343017578125,1400.038330078125],"widgets_values":{"save_output":true,"filename_prefix":"AnimateDiff","loop_count":0,"pix_fmt":"yuv420p","save_metadata":true,"crf":19,"trim_to_audio":false,"videopreview":{"paused":false,"hidden":false,"params":{"filename":"AnimateDiff_00002_p82_jefmt_1758013197.mp4","workflow":"AnimateDiff_00002_p82.png","fullpath":"/data/ComfyUI/personal/0c5e29f80acd84973c41e3a9c4cab22f/output/AnimateDiff_00002_p82.mp4","format":"video/h264-mp4","subfolder":"","type":"output","frame_rate":16}},"format":"video/h264-mp4","no_preview":false,"frame_rate":16,"pingpong":false},"inputs":[{"name":"images","link":172,"label":"images","type":"IMAGE","localized_name":"images"},{"shape":7,"name":"audio","label":"audio","type":"AUDIO","localized_name":"audio"},{"shape":7,"name":"meta_batch","label":"meta_batch","type":"VHS_BatchManager","localized_name":"meta_batch"},{"shape":7,"name":"vae","label":"vae","type":"VAE","localized_name":"vae"},{"widget":{"name":"frame_rate"},"name":"frame_rate","label":"frame_rate","type":"FLOAT","localized_name":"frame_rate"},{"widget":{"name":"loop_count"},"name":"loop_count","label":"loop_count","type":"INT","localized_name":"loop_count"},{"widget":{"name":"filename_prefix"},"name":"filename_prefix","label":"filename_prefix","type":"STRING","localized_name":"filename_prefix"},{"widget":{"name":"format"},"name":"format","label":"format","type":"COMBO","localized_name":"format"},{"widget":{"name":"pingpong"},"name":"pingpong","label":"pingpong","type":"BOOLEAN","localized_name":"pingpong"},{"widget":{"name":"save_output"},"name":"save_output","label":"save_output","type":"BOOLEAN","localized_name":"save_output"},{"widget":{"name":"no_preview"},"shape":7,"name":"no_preview","label":"no_preview","type":"BOOLEAN","localized_name":"no_preview"}],"flags":{},"id":47,"type":"VHS_VideoCombine","properties":{"widget_ue_connectable":{},"Node name for S&R":"VHS_VideoCombine"},"order":22},{"mode":0,"outputs":[{"name":"IMAGE","links":[172],"label":"IMAGE","type":"IMAGE","localized_name":"IMAGE"}],"size":[270,82],"pos":[2777.845458984375,1535.4378662109375],"widgets_values":[1536,"bicubic"],"inputs":[{"name":"image","link":170,"label":"image","type":"IMAGE","localized_name":"image"},{"widget":{"name":"size"},"name":"size","label":"size","type":"INT","localized_name":"size"},{"widget":{"name":"interpolation"},"name":"interpolation","label":"interpolation","type":"COMBO","localized_name":"interpolation"}],"flags":{},"id":45,"type":"PDIMAGE_LongerSize","properties":{"widget_ue_connectable":{},"Node name for S&R":"PDIMAGE_LongerSize"},"order":21},{"mode":0,"outputs":[{"name":"MODEL","links":[173],"label":"MODEL","type":"MODEL","localized_name":"MODEL"},{"name":"CLIP","links":[152,153],"label":"CLIP","type":"CLIP","localized_name":"CLIP"},{"name":"VAE","links":[154,155],"label":"VAE","type":"VAE","localized_name":"VAE"}],"size":[411.2327880859375,98],"pos":[717.7600708007812,992.8963623046875],"widgets_values":["wan2.2-rapid-mega-aio-v1.safetensors"],"inputs":[{"widget":{"name":"ckpt_name"},"name":"ckpt_name","label":"ckpt_name","type":"COMBO","localized_name":"ckpt_name"}],"flags":{},"id":26,"type":"CheckpointLoaderSimple","properties":{"widget_ue_connectable":{},"Node name for S&R":"CheckpointLoaderSimple"},"order":1},{"mode":0,"outputs":[{"name":"MODEL","links":[174],"label":"MODEL","type":"MODEL","localized_name":"MODEL"}],"size":[270,58],"pos":[1114.4764404296875,677.8213500976562],"widgets_values":[true],"inputs":[{"name":"model","link":173,"label":"model","type":"MODEL","localized_name":"model"},{"widget":{"name":"use_SageAttention"},"name":"use_SageAttention","label":"use_SageAttention","type":"BOOLEAN","localized_name":"use_SageAttention"}],"flags":{},"id":48,"type":"ApplySageAttention","properties":{"widget_ue_connectable":{},"Node name for S&R":"ApplySageAttention"},"order":8},{"mode":0,"outputs":[{"name":"IMAGE","links":[163],"label":"IMAGE","type":"IMAGE","localized_name":"IMAGE"},{"name":"width","label":"width","type":"INT","localized_name":"width"},{"name":"height","label":"height","type":"INT","localized_name":"height"},{"name":"mask","label":"mask","type":"MASK","localized_name":"mask"}],"size":[270,286],"pos":[320.9214782714844,1044.93408203125],"widgets_values":[512,512,"nearest-exact","crop","0, 0, 0","center",2,"gpu"],"inputs":[{"name":"image","link":178,"label":"image","type":"IMAGE","localized_name":"image"},{"shape":7,"name":"mask","label":"mask","type":"MASK","localized_name":"mask"},{"widget":{"name":"width"},"name":"width","link":164,"label":"width","type":"INT","localized_name":"width"},{"widget":{"name":"height"},"name":"height","link":165,"label":"height","type":"INT","localized_name":"height"},{"widget":{"name":"upscale_method"},"name":"upscale_method","label":"upscale_method","type":"COMBO","localized_name":"upscale_method"},{"widget":{"name":"keep_proportion"},"name":"keep_proportion","label":"keep_proportion","type":"COMBO","localized_name":"keep_proportion"},{"widget":{"name":"pad_color"},"name":"pad_color","label":"pad_color","type":"STRING","localized_name":"pad_color"},{"widget":{"name":"crop_position"},"name":"crop_position","label":"crop_position","type":"COMBO","localized_name":"crop_position"},{"widget":{"name":"divisible_by"},"name":"divisible_by","label":"divisible_by","type":"INT","localized_name":"divisible_by"},{"widget":{"name":"device"},"shape":7,"name":"device","label":"device","type":"COMBO","localized_name":"device"}],"flags":{},"id":42,"type":"ImageResizeKJv2","properties":{"widget_ue_connectable":{},"Node name for S&R":"ImageResizeKJv2"},"order":14},{"mode":0,"outputs":[{"name":"CONDITIONING","links":[136],"label":"CONDITIONING","type":"CONDITIONING","localized_name":"CONDITIONING"}],"size":[400,200],"pos":[735.2056274414062,1159.9134521484375],"widgets_values":["花开"],"inputs":[{"name":"clip","link":152,"label":"clip","type":"CLIP","localized_name":"clip"},{"widget":{"name":"text"},"name":"text","label":"text","type":"STRING","localized_name":"text"}],"flags":{},"id":9,"type":"CLIPTextEncode","properties":{"widget_ue_connectable":{},"Node name for S&R":"CLIPTextEncode"},"order":9},{"outputs":[{"name":"IMAGE","links":[175,176,177],"label":"IMAGE","type":"IMAGE","localized_name":"IMAGE"},{"name":"MASK","label":"MASK","type":"MASK","localized_name":"MASK"}],"color":"#223","widgets_values":["e1d4cf6249ec7321364b291d82808b2370d20aa976543ce3228b34e388f9f331.png","image"],"inputs":[{"widget":{"name":"image"},"name":"image","label":"image","type":"COMBO","localized_name":"image"},{"widget":{"name":"upload"},"name":"upload","label":"upload","type":"IMAGEUPLOAD","localized_name":"choose file to upload"}],"flags":{},"type":"LoadImage","mode":0,"bgcolor":"#335","size":[342.5999755859375,314],"pos":[-209.63015747070312,329.25262451171875],"id":49,"properties":{"cnr_id":"comfy-core","ver":"0.3.30","widget_ue_connectable":{},"Node name for S&R":"LoadImage","ttNbgOverride":{"bgcolor":"#335","groupcolor":"#88A","color":"#223"}},"order":2},{"mode":0,"outputs":[{"name":"Filenames","label":"Filenames","type":"VHS_FILENAMES","localized_name":"Filenames"}],"size":[214.7587890625,566.7587890625],"pos":[2349.8701171875,726.0950927734375],"widgets_values":{"save_output":true,"filename_prefix":"AnimateDiff","loop_count":0,"pix_fmt":"yuv420p","save_metadata":true,"crf":19,"trim_to_audio":false,"videopreview":{"paused":false,"hidden":false,"params":{"filename":"AnimateDiff_00001_p82_cnmot_1758013182.mp4","workflow":"AnimateDiff_00001_p82.png","fullpath":"/data/ComfyUI/personal/0c5e29f80acd84973c41e3a9c4cab22f/output/AnimateDiff_00001_p82.mp4","format":"video/h264-mp4","subfolder":"","type":"output","frame_rate":16}},"format":"video/h264-mp4","no_preview":false,"frame_rate":16,"pingpong":false},"inputs":[{"name":"images","link":171,"label":"images","type":"IMAGE","localized_name":"images"},{"shape":7,"name":"audio","label":"audio","type":"AUDIO","localized_name":"audio"},{"shape":7,"name":"meta_batch","label":"meta_batch","type":"VHS_BatchManager","localized_name":"meta_batch"},{"shape":7,"name":"vae","label":"vae","type":"VAE","localized_name":"vae"},{"widget":{"name":"frame_rate"},"name":"frame_rate","label":"frame_rate","type":"FLOAT","localized_name":"frame_rate"},{"widget":{"name":"loop_count"},"name":"loop_count","label":"loop_count","type":"INT","localized_name":"loop_count"},{"widget":{"name":"filename_prefix"},"name":"filename_prefix","label":"filename_prefix","type":"STRING","localized_name":"filename_prefix"},{"widget":{"name":"format"},"name":"format","label":"format","type":"COMBO","localized_name":"format"},{"widget":{"name":"pingpong"},"name":"pingpong","label":"pingpong","type":"BOOLEAN","localized_name":"pingpong"},{"widget":{"name":"save_output"},"name":"save_output","label":"save_output","type":"BOOLEAN","localized_name":"save_output"},{"widget":{"name":"no_preview"},"shape":7,"name":"no_preview","label":"no_preview","type":"BOOLEAN","localized_name":"no_preview"}],"flags":{},"id":46,"type":"VHS_VideoCombine","properties":{"widget_ue_connectable":{},"Node name for S&R":"VHS_VideoCombine"},"order":20},{"outputs":[{"name":"IMAGE","links":[178,179],"label":"IMAGE","type":"IMAGE","localized_name":"IMAGE"},{"name":"MASK","label":"MASK","type":"MASK","localized_name":"MASK"}],"color":"#223","widgets_values":["4fd7704b0a5f4b29bcb010e938d22757244ba1057fa3f5825ba1ef927759b9ef.png","image"],"inputs":[{"widget":{"name":"image"},"name":"image","label":"image","type":"COMBO","localized_name":"image"},{"widget":{"name":"upload"},"name":"upload","label":"upload","type":"IMAGEUPLOAD","localized_name":"choose file to upload"}],"flags":{},"type":"LoadImage","mode":0,"bgcolor":"#335","size":[342.5999755859375,314.00006103515625],"pos":[-179.16229248046875,1004.1016235351562],"id":50,"properties":{"cnr_id":"comfy-core","ver":"0.3.30","widget_ue_connectable":{},"Node name for S&R":"LoadImage","ttNbgOverride":{"bgcolor":"#335","groupcolor":"#88A","color":"#223"}},"order":3},{"mode":0,"outputs":[{"name":"INT","links":[180,181],"label":"INT","type":"INT","localized_name":"INT"}],"size":[270,58],"pos":[-156.7445068359375,849.4998779296875],"widgets_values":[81],"inputs":[{"widget":{"name":"value"},"name":"value","label":"value","type":"INT","localized_name":"value"}],"flags":{},"id":51,"type":"JWInteger","properties":{"widget_ue_connectable":{},"Node name for S&R":"JWInteger"},"order":4},{"mode":0,"outputs":[{"name":"INT","links":[182],"label":"INT","type":"INT","localized_name":"INT"}],"size":[270,58],"pos":[-161.07464599609375,696.9241943359375],"widgets_values":[1024],"inputs":[{"widget":{"name":"value"},"name":"value","label":"value","type":"INT","localized_name":"value"}],"flags":{},"id":52,"type":"JWInteger","properties":{"widget_ue_connectable":{},"Node name for S&R":"JWInteger"},"order":5},{"outputs":[],"color":"#432","widgets_values":["最长边"],"inputs":[],"flags":{},"type":"Note","mode":0,"bgcolor":"#653","size":[140,60],"pos":[-425.8363342285156,706.8968505859375],"id":53,"properties":{},"order":6},{"outputs":[],"color":"#432","widgets_values":["最长边"],"inputs":[],"flags":{},"type":"Note","mode":0,"bgcolor":"#653","size":[140,60],"pos":[-401.518798828125,844.3600463867188],"id":54,"properties":{},"order":7}],"extra":{"VHS_KeepIntermediate":true,"links_added_by_ue":[],"ue_links":[],"VHS_MetadataImage":true,"0246.VERSION":[0,0,4],"VHS_latentpreviewrate":0,"frontendVersion":"1.25.11","VHS_latentpreview":false,"ds":{"offset":[863.240886074702,-137.02902023686676],"scale":0.7247295000000031}},"groups":[{"color":"#3f789e","font_size":240,"flags":{},"id":1,"title":"B站、Youtube：T8star-Aix","bounding":[-969.4401245117188,-338.2389221191406,4168,309]}],"links":[[123,32,0,8,0,"MODEL"],[136,9,0,28,0,"CONDITIONING"],[137,10,0,28,1,"CONDITIONING"],[141,34,0,28,3,"IMAGE"],[143,28,2,8,3,"LATENT"],[144,28,0,8,1,"CONDITIONING"],[145,28,1,8,2,"CONDITIONING"],[148,34,1,28,4,"MASK"],[149,8,0,11,0,"LATENT"],[152,26,1,9,0,"CLIP"],[153,26,1,10,0,"CLIP"],[154,26,2,28,2,"VAE"],[155,26,2,11,1,"VAE"],[163,42,0,34,1,"IMAGE"],[164,41,3,42,2,"INT"],[165,41,4,42,3,"INT"],[168,43,0,44,0,"IMAGE"],[169,11,0,44,1,"IMAGE"],[170,44,0,45,0,"IMAGE"],[171,11,0,46,0,"IMAGE"],[172,45,0,47,0,"IMAGE"],[173,26,0,48,0,"MODEL"],[174,48,0,32,0,"MODEL"],[175,49,0,34,0,"IMAGE"],[176,49,0,41,0,"IMAGE"],[177,49,0,43,0,"IMAGE"],[178,50,0,42,0,"IMAGE"],[179,50,0,43,1,"IMAGE"],[180,51,0,34,4,"INT"],[181,51,0,28,8,"INT"],[182,52,0,41,9,"INT"]],"id":"e6c78bba-ef40-40c6-8b95-20bd0020ddbb","config":{},"version":0.4,"last_node_id":54,"revision":0}